{"LanguageId":1,"WhiteLabelId":3,"LiveWhitelabelId":12,"CustomerId":0,"UserId":0,"ShopUserId":0,"Ticket":0,"Type":"","TypeIns":0,"BetIdAuth":0,"Proposal":false,"IsOnlineAuth":false,"ShowSystem":1,"Amount":0.0,"MaxWinAmount":79228162514264337593543950335.0,"ErrorCode":"","ErrorDescription":"Odds Have Changed.","AjaxCallForCheckOdds":true,"FormData":{},"SlipEventCollection":[{"Id":4919135,"EventCode":1,"Game":{"Id":1,"Name":"Soccer"},"Country":{"Id":601,"Name":"ENGLAND"},"Group":{"Id":50342,"Name":"MATCHES - 1X2 and other odds"},"League":{"Id":1,"Name":"England Premier League"},"MatchDescription":"Manchester United - Tottenham","Team1":"Manchester United","Team2":"Tottenham","IsInvalid":false,"SelectionCollection":{"(966, 1, 0, 0)":{"GameId":1,"MarketId":185,"OddId":966,"SpecialBetValueId":1,"ChangeSpecialBetValueInSlip":false,"SpecialBetValue":"","Symbol":"1*","MarketName":"1X2 0%","MarketDescription":"What will the result be at the end of Regular time (FT).","OddName":"1","OddDescription":"1","SpecialValue":0.0,"TeamId":0,"PlayerId":0,"TeamOrder":null,"PlayerName":"","MarketNameWithSpecialValue":"1X2 0%","OddNameWithSpecialValue":"1","OddNewDescriptionWithSpecialValue":"1","SymbolWithSpecialValue":"1*","OddDescriptionWithSpecialValue":"1","MarketNameFromTemplate":"1X2 0%","OddNameFromTemplate":" Manchester United","IsCustomBetSelection":false}}},{"Id":4928535,"EventCode":1,"Game":{"Id":1,"Name":"Soccer"},"Country":{"Id":430,"Name":"KOREA SOUTH"},"Group":{"Id":50342,"Name":"MATCHES - 1X2 and other odds"},"League":{"Id":5827,"Name":"South Korea K League 1"},"MatchDescription":"Bucheon FC - Gyeongnam FC","Team1":"Bucheon FC","Team2":"Gyeongnam FC","IsInvalid":false,"SelectionCollection":{"(100001, 1, 0, 0)":{"GameId":1,"MarketId":10001,"OddId":100001,"SpecialBetValueId":1,"ChangeSpecialBetValueInSlip":false,"SpecialBetValue":"","Symbol":"10001-1","MarketName":"3way","MarketDescription":"3way","OddName":"1","OddDescription":"1","SpecialValue":0.0,"TeamId":0,"PlayerId":0,"TeamOrder":null,"PlayerName":"","MarketNameWithSpecialValue":"3way","OddNameWithSpecialValue":"1","OddNewDescriptionWithSpecialValue":"1","SymbolWithSpecialValue":"10001-1","OddDescriptionWithSpecialValue":"1","MarketNameFromTemplate":"3way","OddNameFromTemplate":" Bucheon FC","IsCustomBetSelection":false}}},{"Id":4916274,"EventCode":1,"Game":{"Id":1,"Name":"Soccer"},"Country":{"Id":277,"Name":"AZERBAIJAN"},"Group":{"Id":50342,"Name":"MATCHES - 1X2 and other odds"},"League":{"Id":7078,"Name":"Azerbaijan First Division"},"MatchDescription":"Zira Fk 2 - Energetik Mingechevir","Team1":"Zira Fk 2","Team2":"Energetik Mingechevir","IsInvalid":false,"SelectionCollection":{"(100001, 1, 0, 0)":{"GameId":1,"MarketId":10001,"OddId":100001,"SpecialBetValueId":1,"ChangeSpecialBetValueInSlip":false,"SpecialBetValue":"","Symbol":"10001-1","MarketName":"3way","MarketDescription":"3way","OddName":"1","OddDescription":"1","SpecialValue":0.0,"TeamId":0,"PlayerId":0,"TeamOrder":null,"PlayerName":"","MarketNameWithSpecialValue":"3way","OddNameWithSpecialValue":"1","OddNewDescriptionWithSpecialValue":"1","SymbolWithSpecialValue":"10001-1","OddDescriptionWithSpecialValue":"1","MarketNameFromTemplate":"3way","OddNameFromTemplate":" Zira Fk 2","IsCustomBetSelection":false}}},{"Id":4918528,"EventCode":1,"Game":{"Id":1,"Name":"Soccer"},"Country":{"Id":399,"Name":"ETHIOPIA"},"Group":{"Id":50342,"Name":"MATCHES - 1X2 and other odds"},"League":{"Id":7661,"Name":"Ethiopia Premier League "},"MatchDescription":"Arba Minch Kenema - Hadiya Hossana FC","Team1":"Arba Minch Kenema","Team2":"Hadiya Hossana FC","IsInvalid":false,"SelectionCollection":{"(100002, 1, 0, 0)":{"GameId":1,"MarketId":10001,"OddId":100002,"SpecialBetValueId":1,"ChangeSpecialBetValueInSlip":false,"SpecialBetValue":"","Symbol":"10001-x","MarketName":"3way","MarketDescription":"3way","OddName":"X","OddDescription":"x","SpecialValue":0.0,"TeamId":0,"PlayerId":0,"TeamOrder":null,"PlayerName":"","MarketNameWithSpecialValue":"3way","OddNameWithSpecialValue":"X","OddNewDescriptionWithSpecialValue":"x","SymbolWithSpecialValue":"10001-x","OddDescriptionWithSpecialValue":"x","MarketNameFromTemplate":"3way","OddNameFromTemplate":" Draw","IsCustomBetSelection":false}}},{"Id":4917809,"EventCode":1,"Game":{"Id":1,"Name":"Soccer"},"Country":{"Id":211,"Name":"ITALY "},"Group":{"Id":50342,"Name":"MATCHES - 1X2 and other odds"},"League":{"Id":7238,"Name":"Italy Primavera Cup"},"MatchDescription":"Empoli - Ascoli","Team1":"Empoli","Team2":"Ascoli","IsInvalid":false,"SelectionCollection":{"(100003, 1, 0, 0)":{"GameId":1,"MarketId":10001,"OddId":100003,"SpecialBetValueId":1,"ChangeSpecialBetValueInSlip":false,"SpecialBetValue":"","Symbol":"10001-2","MarketName":"3way","MarketDescription":"3way","OddName":"2","OddDescription":"2","SpecialValue":0.0,"TeamId":0,"PlayerId":0,"TeamOrder":null,"PlayerName":"","MarketNameWithSpecialValue":"3way","OddNameWithSpecialValue":"2","OddNewDescriptionWithSpecialValue":"2","SymbolWithSpecialValue":"10001-2","OddDescriptionWithSpecialValue":"2","MarketNameFromTemplate":"3way","OddNameFromTemplate":" Ascoli","IsCustomBetSelection":false}}},{"Id":4917578,"EventCode":1,"Game":{"Id":1,"Name":"Soccer"},"Country":{"Id":455,"Name":"MYANMAR"},"Group":{"Id":50343,"Name":"ONLY LIVE MATCHES - 1X2 and other odds"},"League":{"Id":7467,"Name":"Myanmar National League"},"MatchDescription":"Myawady Fc - Yadanarbon","Team1":"Myawady Fc","Team2":"Yadanarbon","IsInvalid":false,"SelectionCollection":{"(100003, 1, 0, 0)":{"GameId":1,"MarketId":10001,"OddId":100003,"SpecialBetValueId":1,"ChangeSpecialBetValueInSlip":false,"SpecialBetValue":"","Symbol":"10001-2","MarketName":"3way","MarketDescription":"3way","OddName":"2","OddDescription":"2","SpecialValue":0.0,"TeamId":0,"PlayerId":0,"TeamOrder":null,"PlayerName":"","MarketNameWithSpecialValue":"3way","OddNameWithSpecialValue":"2","OddNewDescriptionWithSpecialValue":"2","SymbolWithSpecialValue":"10001-2","OddDescriptionWithSpecialValue":"2","MarketNameFromTemplate":"3way","OddNameFromTemplate":" Yadanarbon","IsCustomBetSelection":false}}}],"Combinations":[{"Enabled":true,"CounterLines":1,"TotalLines":6,"CombinationsProduced":6,"MultiplesSelections":1,"AverageMultiplierMin":1.96719093260706,"AverageMultiplierMax":1.96719093260706,"BonusMin":0.0,"BonusMax":0.0,"BetAmount":0.0,"BetColAmount":0.0,"BetMulAmount":0.0,"BetAmountView":0.0,"BetColAmountView":0.0,"BetMulAmountView":0.0,"MinimumMultiplier":1.07,"MaximumMultiplier":2.66,"MinimumMultpilierWithBonus":1.07,"MaximumMultiplierWithBonus":2.66},{"Enabled":true,"CounterLines":2,"TotalLines":6,"CombinationsProduced":15,"MultiplesSelections":1,"AverageMultiplierMin":3.86984016533146,"AverageMultiplierMax":3.86984016533146,"BonusMin":0.0,"BonusMax":0.0,"BetAmount":0.0,"BetColAmount":0.0,"BetMulAmount":0.0,"BetAmountView":0.0,"BetColAmountView":0.0,"BetMulAmountView":0.0,"MinimumMultiplier":1.4231,"MaximumMultiplier":6.7298,"MinimumMultpilierWithBonus":1.4231,"MaximumMultiplierWithBonus":6.7298},{"Enabled":true,"CounterLines":3,"TotalLines":6,"CombinationsProduced":20,"MultiplesSelections":1,"AverageMultiplierMin":7.61271448387866,"AverageMultiplierMax":7.61271448387866,"BonusMin":0.0,"BonusMax":0.0,"BetAmount":0.0,"BetColAmount":0.0,"BetMulAmount":0.0,"BetAmountView":0.0,"BetColAmountView":0.0,"BetMulAmountView":0.0,"MinimumMultiplier":3.472364,"MaximumMultiplier":16.689904,"MinimumMultpilierWithBonus":3.472364,"MaximumMultiplierWithBonus":16.689904},{"Enabled":true,"CounterLines":4,"TotalLines":6,"CombinationsProduced":15,"MultiplesSelections":1,"AverageMultiplierMin":14.9756629052126,"AverageMultiplierMax":14.9756629052126,"BonusMin":0.0,"BonusMax":0.0,"BetAmount":0.0,"BetColAmount":0.0,"BetMulAmount":0.0,"BetAmountView":0.0,"BetColAmountView":0.0,"BetMulAmountView":0.0,"MinimumMultiplier":8.61146272,"MaximumMultiplier":40.72336576,"MinimumMultpilierWithBonus":8.61146272,"MaximumMultiplierWithBonus":40.72336576},{"Enabled":true,"CounterLines":5,"TotalLines":6,"CombinationsProduced":6,"MultiplesSelections":1,"AverageMultiplierMin":29.4599882769142,"AverageMultiplierMax":29.4599882769142,"BonusMin":0.0,"BonusMax":0.0,"BetAmount":0.0,"BetColAmount":0.0,"BetMulAmount":0.0,"BetAmountView":0.0,"BetColAmountView":0.0,"BetMulAmountView":0.0,"MinimumMultiplier":21.7870006816,"MaximumMultiplier":54.1620764608,"MinimumMultpilierWithBonus":21.7870006816,"MaximumMultiplierWithBonus":54.1620764608},{"Enabled":true,"CounterLines":6,"TotalLines":6,"CombinationsProduced":1,"MultiplesSelections":1,"AverageMultiplierMin":57.953421813056,"AverageMultiplierMax":57.953421813056,"BonusMin":0.0,"BonusMax":0.0,"BetAmount":0.0,"BetColAmount":0.0,"BetMulAmount":0.0,"BetAmountView":0.0,"BetColAmountView":0.0,"BetMulAmountView":0.0,"MinimumMultiplier":57.953421813056,"MaximumMultiplier":57.953421813056,"MinimumMultpilierWithBonus":57.953421813056,"MaximumMultiplierWithBonus":57.953421813056}],"BetSlip":{"Combinations":[{"CounterLines":1,"TotalLines":6,"CombinationsProduced":6,"MultiplesSelections":1,"AverageMultiplierMin":1.96719093260706,"AverageMultiplierMax":1.96719093260706,"BonusMin":0.0,"BonusMax":0.0,"MinimumMultpilierWithBonus":1.07,"MaximumMultiplierWithBonus":2.66,"MinimumMultpilier":1.07,"MaximumMultiplier":2.66,"Amount":0.0,"AmountPerColumn":0.0,"Enabled":true},{"CounterLines":2,"TotalLines":6,"CombinationsProduced":15,"MultiplesSelections":1,"AverageMultiplierMin":3.86984016533146,"AverageMultiplierMax":3.86984016533146,"BonusMin":0.0,"BonusMax":0.0,"MinimumMultpilierWithBonus":1.4231,"MaximumMultiplierWithBonus":6.7298,"MinimumMultpilier":1.4231,"MaximumMultiplier":6.7298,"Amount":0.0,"AmountPerColumn":0.0,"Enabled":true},{"CounterLines":3,"TotalLines":6,"CombinationsProduced":20,"MultiplesSelections":1,"AverageMultiplierMin":7.61271448387866,"AverageMultiplierMax":7.61271448387866,"BonusMin":0.0,"BonusMax":0.0,"MinimumMultpilierWithBonus":3.472364,"MaximumMultiplierWithBonus":16.689904,"MinimumMultpilier":3.472364,"MaximumMultiplier":16.689904,"Amount":0.0,"AmountPerColumn":0.0,"Enabled":true},{"CounterLines":4,"TotalLines":6,"CombinationsProduced":15,"MultiplesSelections":1,"AverageMultiplierMin":14.9756629052126,"AverageMultiplierMax":14.9756629052126,"BonusMin":0.0,"BonusMax":0.0,"MinimumMultpilierWithBonus":8.61146272,"MaximumMultiplierWithBonus":40.72336576,"MinimumMultpilier":8.61146272,"MaximumMultiplier":40.72336576,"Amount":0.0,"AmountPerColumn":0.0,"Enabled":true},{"CounterLines":5,"TotalLines":6,"CombinationsProduced":6,"MultiplesSelections":1,"AverageMultiplierMin":29.4599882769142,"AverageMultiplierMax":29.4599882769142,"BonusMin":0.0,"BonusMax":0.0,"MinimumMultpilierWithBonus":21.7870006816,"MaximumMultiplierWithBonus":54.1620764608,"MinimumMultpilier":21.7870006816,"MaximumMultiplier":54.1620764608,"Amount":0.0,"AmountPerColumn":0.0,"Enabled":true},{"CounterLines":6,"TotalLines":6,"CombinationsProduced":1,"MultiplesSelections":1,"AverageMultiplierMin":57.953421813056,"AverageMultiplierMax":57.953421813056,"BonusMin":0.0,"BonusMax":0.0,"MinimumMultpilierWithBonus":57.953421813056,"MaximumMultiplierWithBonus":57.953421813056,"MinimumMultpilier":57.953421813056,"MaximumMultiplier":57.953421813056,"Amount":0.0,"AmountPerColumn":0.0,"Enabled":true}],"WhiteLabelId":3,"LiveWhiteLabelId":12,"SiteId":54,"MinimumAccepted":1,"GroupBonus":0.0,"ErrorFlag":0,"HasLive":true,"MultiplesBets":1,"NumberOfBankers":0,"NumberOfNoBankers":6,"IsFreeBet":false,"TotalOdds":57.953421813056,"System":0,"SystemClicked":false,"Events":[{"SportEventId":4919135,"Banker":false,"EventScoreMetaInfo":"","Selections":[{"SportEventId":4919135,"MarketId":185,"OddId":966,"SpecialBetValueId":1,"IsLive":false,"ChangeSpecialBetValueInSlip":false,"OddValue":2.53,"SpecialValue":0.0,"TeamId":0,"PlayerId":0,"TeamOrder":null,"Banker":false,"Minimum":1,"IsCustomBetSelection":false,"HasChanges":false,"Probability":0.4014}],"SlipEventLocalized":{"SportEventId":4919135,"EventCode":1,"Game":{"Id":1,"Name":"Soccer"},"Country":{"Id":601,"Name":"ENGLAND"},"Group":{"Id":50342,"Name":"MATCHES - 1X2 and other odds","AntePostMarkets":0,"MainType":0},"League":{"Id":1,"Name":"England Premier League"},"MatchDescription":"Manchester United - Tottenham","Team1":"Manchester United","Team2":"Tottenham","IsInvalid":false,"SelectionCollection":{"966_1_0_0":{"GameId":1,"SportEventId":4919135,"MarketId":185,"OddId":966,"SpecialBetValueId":1,"ChangeSpecialBetValueInSlip":false,"SpecialBetValue":"","Symbol":"1*","MarketName":"1X2 0%","MarketDescription":"What will the result be at the end of Regular time (FT).","OddName":"1","OddDescription":"1","SpecialValue":0.0,"TeamId":0,"PlayerId":0,"TeamOrder":null,"PlayerName":"","MarketNameWithSpecialValue":"1X2 0%","OddNameWithSpecialValue":"1","OddNewDescriptionWithSpecialValue":"1","SymbolWithSpecialValue":"1*","OddDescriptionWithSpecialValue":"1","OddValue":2.53,"MarketNameFromTemplate":"1X2 0%","OddNameFromTemplate":" Manchester United","IsCustomBetSelection":false,"CustomBetOddValue":0.0,"CustomBetProbability":0.0}},"IsActive":true,"Results":[],"ResultsString":"","LanguageId":1},"IsCustomBetEvent":false,"CustomBetOddValue":0.0,"CustomBetProbability":0.0},{"SportEventId":4928535,"Banker":false,"EventScoreMetaInfo":"{\"score\":\"0:0\",\"gamescore\":\"\",\"setscore\":\"0:0\",\"matchminute\":\"40\"}","Selections":[{"SportEventId":4928535,"MarketId":10001,"OddId":100001,"SpecialBetValueId":1,"IsLive":true,"ChangeSpecialBetValueInSlip":false,"OddValue":2.64,"SpecialValue":0.0,"TeamId":0,"PlayerId":0,"TeamOrder":null,"Banker":false,"Minimum":1,"IsCustomBetSelection":false,"HasChanges":false,"Probability":0.35570288}],"SlipEventLocalized":{"SportEventId":4928535,"EventCode":1,"Game":{"Id":1,"Name":"Soccer"},"Country":{"Id":430,"Name":"KOREA SOUTH"},"Group":{"Id":50342,"Name":"MATCHES - 1X2 and other odds","AntePostMarkets":0,"MainType":0},"League":{"Id":5827,"Name":"South Korea K League 1"},"MatchDescription":"Bucheon FC - Gyeongnam FC","Team1":"Bucheon FC","Team2":"Gyeongnam FC","IsInvalid":false,"SelectionCollection":{"100001_1_0_0":{"GameId":1,"SportEventId":4928535,"MarketId":10001,"OddId":100001,"SpecialBetValueId":1,"ChangeSpecialBetValueInSlip":false,"SpecialBetValue":"","Symbol":"10001-1","MarketName":"3way","MarketDescription":"3way","OddName":"1","OddDescription":"1","SpecialValue":0.0,"TeamId":0,"PlayerId":0,"TeamOrder":null,"PlayerName":"","MarketNameWithSpecialValue":"3way","OddNameWithSpecialValue":"1","OddNewDescriptionWithSpecialValue":"1","SymbolWithSpecialValue":"10001-1","OddDescriptionWithSpecialValue":"1","OddValue":2.64,"MarketNameFromTemplate":"3way","OddNameFromTemplate":" Bucheon FC","IsCustomBetSelection":false,"CustomBetOddValue":0.0,"CustomBetProbability":0.0}},"IsActive":true,"Results":[],"ResultsString":"","LanguageId":1},"IsCustomBetEvent":false,"CustomBetOddValue":0.0,"CustomBetProbability":0.0},{"SportEventId":4916274,"Banker":false,"EventScoreMetaInfo":"{\"score\":\"1:0\",\"gamescore\":\"\",\"setscore\":\"1:0#0:0\",\"matchminute\":\"81\"}","Selections":[{"SportEventId":4916274,"MarketId":10001,"OddId":100001,"SpecialBetValueId":1,"IsLive":true,"ChangeSpecialBetValueInSlip":false,"OddValue":0.0,"SpecialValue":0.0,"TeamId":0,"PlayerId":0,"TeamOrder":null,"Banker":false,"Minimum":1,"IsCustomBetSelection":false,"HasChanges":false,"Probability":0.0}],"SlipEventLocalized":{"SportEventId":4916274,"EventCode":1,"Game":{"Id":1,"Name":"Soccer"},"Country":{"Id":277,"Name":"AZERBAIJAN"},"Group":{"Id":50342,"Name":"MATCHES - 1X2 and other odds","AntePostMarkets":0,"MainType":0},"League":{"Id":7078,"Name":"Azerbaijan First Division"},"MatchDescription":"Zira Fk 2 - Energetik Mingechevir","Team1":"Zira Fk 2","Team2":"Energetik Mingechevir","IsInvalid":false,"SelectionCollection":{"100001_1_0_0":{"GameId":1,"SportEventId":4916274,"MarketId":10001,"OddId":100001,"SpecialBetValueId":1,"ChangeSpecialBetValueInSlip":false,"SpecialBetValue":"","Symbol":"10001-1","MarketName":"3way","MarketDescription":"3way","OddName":"1","OddDescription":"1","SpecialValue":0.0,"TeamId":0,"PlayerId":0,"TeamOrder":null,"PlayerName":"","MarketNameWithSpecialValue":"3way","OddNameWithSpecialValue":"1","OddNewDescriptionWithSpecialValue":"1","SymbolWithSpecialValue":"10001-1","OddDescriptionWithSpecialValue":"1","OddValue":0.0,"MarketNameFromTemplate":"3way","OddNameFromTemplate":" Zira Fk 2","IsCustomBetSelection":false,"CustomBetOddValue":0.0,"CustomBetProbability":0.0}},"IsActive":true,"Results":[],"ResultsString":"","LanguageId":1},"IsCustomBetEvent":false,"CustomBetOddValue":0.0,"CustomBetProbability":0.0},{"SportEventId":4918528,"Banker":false,"EventScoreMetaInfo":"{\"score\":\"0:0\",\"gamescore\":\"\",\"setscore\":\"0:0\",\"matchminute\":\"41\"}","Selections":[{"SportEventId":4918528,"MarketId":10001,"OddId":100002,"SpecialBetValueId":1,"IsLive":true,"ChangeSpecialBetValueInSlip":false,"OddValue":2.46,"SpecialValue":0.0,"TeamId":0,"PlayerId":0,"TeamOrder":null,"Banker":false,"Minimum":1,"IsCustomBetSelection":false,"HasChanges":false,"Probability":0.37025102}],"SlipEventLocalized":{"SportEventId":4918528,"EventCode":1,"Game":{"Id":1,"Name":"Soccer"},"Country":{"Id":399,"Name":"ETHIOPIA"},"Group":{"Id":50342,"Name":"MATCHES - 1X2 and other odds","AntePostMarkets":0,"MainType":0},"League":{"Id":7661,"Name":"Ethiopia Premier League "},"MatchDescription":"Arba Minch Kenema - Hadiya Hossana FC","Team1":"Arba Minch Kenema","Team2":"Hadiya Hossana FC","IsInvalid":false,"SelectionCollection":{"100002_1_0_0":{"GameId":1,"SportEventId":4918528,"MarketId":10001,"OddId":100002,"SpecialBetValueId":1,"ChangeSpecialBetValueInSlip":false,"SpecialBetValue":"","Symbol":"10001-x","MarketName":"3way","MarketDescription":"3way","OddName":"X","OddDescription":"x","SpecialValue":0.0,"TeamId":0,"PlayerId":0,"TeamOrder":null,"PlayerName":"","MarketNameWithSpecialValue":"3way","OddNameWithSpecialValue":"X","OddNewDescriptionWithSpecialValue":"x","SymbolWithSpecialValue":"10001-x","OddDescriptionWithSpecialValue":"x","OddValue":2.46,"MarketNameFromTemplate":"3way","OddNameFromTemplate":" Draw","IsCustomBetSelection":false,"CustomBetOddValue":0.0,"CustomBetProbability":0.0}},"IsActive":true,"Results":[],"ResultsString":"","LanguageId":1},"IsCustomBetEvent":false,"CustomBetOddValue":0.0,"CustomBetProbability":0.0},{"SportEventId":4917809,"Banker":false,"EventScoreMetaInfo":"{\"score\":\"1:2\",\"gamescore\":\"\",\"setscore\":\"1:2\",\"matchminute\":\"39\"}","Selections":[{"SportEventId":4917809,"MarketId":10001,"OddId":100003,"SpecialBetValueId":1,"IsLive":true,"ChangeSpecialBetValueInSlip":false,"OddValue":2.44,"SpecialValue":0.0,"TeamId":0,"PlayerId":0,"TeamOrder":null,"Banker":false,"Minimum":1,"IsCustomBetSelection":false,"HasChanges":false,"Probability":0.37361097}],"SlipEventLocalized":{"SportEventId":4917809,"EventCode":1,"Game":{"Id":1,"Name":"Soccer"},"Country":{"Id":211,"Name":"ITALY "},"Group":{"Id":50342,"Name":"MATCHES - 1X2 and other odds","AntePostMarkets":0,"MainType":0},"League":{"Id":7238,"Name":"Italy Primavera Cup"},"MatchDescription":"Empoli - Ascoli","Team1":"Empoli","Team2":"Ascoli","IsInvalid":false,"SelectionCollection":{"100003_1_0_0":{"GameId":1,"SportEventId":4917809,"MarketId":10001,"OddId":100003,"SpecialBetValueId":1,"ChangeSpecialBetValueInSlip":false,"SpecialBetValue":"","Symbol":"10001-2","MarketName":"3way","MarketDescription":"3way","OddName":"2","OddDescription":"2","SpecialValue":0.0,"TeamId":0,"PlayerId":0,"TeamOrder":null,"PlayerName":"","MarketNameWithSpecialValue":"3way","OddNameWithSpecialValue":"2","OddNewDescriptionWithSpecialValue":"2","SymbolWithSpecialValue":"10001-2","OddDescriptionWithSpecialValue":"2","OddValue":2.44,"MarketNameFromTemplate":"3way","OddNameFromTemplate":" Ascoli","IsCustomBetSelection":false,"CustomBetOddValue":0.0,"CustomBetProbability":0.0}},"IsActive":true,"Results":[],"ResultsString":"","LanguageId":1},"IsCustomBetEvent":false,"CustomBetOddValue":0.0,"CustomBetProbability":0.0},{"SportEventId":4917578,"Banker":false,"EventScoreMetaInfo":"{\"score\":\"0:1\",\"gamescore\":\"\",\"setscore\":\"0:1#0:0\",\"matchminute\":\"83\"}","Selections":[{"SportEventId":4917578,"MarketId":10001,"OddId":100003,"SpecialBetValueId":1,"IsLive":true,"ChangeSpecialBetValueInSlip":false,"OddValue":1.33,"SpecialValue":0.0,"TeamId":0,"PlayerId":0,"TeamOrder":null,"Banker":false,"Minimum":1,"IsCustomBetSelection":false,"HasChanges":false,"Probability":0.70604725}],"SlipEventLocalized":{"SportEventId":4917578,"EventCode":1,"Game":{"Id":1,"Name":"Soccer"},"Country":{"Id":455,"Name":"MYANMAR"},"Group":{"Id":50343,"Name":"ONLY LIVE MATCHES - 1X2 and other odds","AntePostMarkets":0,"MainType":0},"League":{"Id":7467,"Name":"Myanmar National League"},"MatchDescription":"Myawady Fc - Yadanarbon","Team1":"Myawady Fc","Team2":"Yadanarbon","IsInvalid":false,"SelectionCollection":{"100003_1_0_0":{"GameId":1,"SportEventId":4917578,"MarketId":10001,"OddId":100003,"SpecialBetValueId":1,"ChangeSpecialBetValueInSlip":false,"SpecialBetValue":"","Symbol":"10001-2","MarketName":"3way","MarketDescription":"3way","OddName":"2","OddDescription":"2","SpecialValue":0.0,"TeamId":0,"PlayerId":0,"TeamOrder":null,"PlayerName":"","MarketNameWithSpecialValue":"3way","OddNameWithSpecialValue":"2","OddNewDescriptionWithSpecialValue":"2","SymbolWithSpecialValue":"10001-2","OddDescriptionWithSpecialValue":"2","OddValue":1.33,"MarketNameFromTemplate":"3way","OddNameFromTemplate":" Yadanarbon","IsCustomBetSelection":false,"CustomBetOddValue":0.0,"CustomBetProbability":0.0}},"IsActive":false,"Results":[],"ResultsString":"","LanguageId":1},"IsCustomBetEvent":false,"CustomBetOddValue":0.0,"CustomBetProbability":0.0}]},"BetResponse":{"ErrorCode":501,"ChangedOdds":[{"OddId":100002,"SpecialBetValueId":1,"ChangeSpecialBetValueInSlip":false,"NewSpecialBetValueId":1,"Symbol":null,"OddValue":2.48,"NewOddValue":2.46,"EventScoreMetaInfo":"{\"score\":\"0:0\",\"gamescore\":\"\",\"setscore\":\"0:0\",\"matchminute\":\"41\"}","ErrorStatus":0,"ErrorMessage":"","Modified":-1,"PlayerId":0,"TeamId":0,"Probability":0.0,"NewProbability":0.0,"CustomBetOddValue":0.0,"CustomBetNewOddValue":0.0,"CustomBetProbability":0.0,"CustomBetNewProbability":0.0,"CustomBetModified":0,"SportEventEventId":4918528},{"OddId":100001,"SpecialBetValueId":1,"ChangeSpecialBetValueInSlip":false,"NewSpecialBetValueId":0,"Symbol":null,"OddValue":1.07,"NewOddValue":0.0,"EventScoreMetaInfo":"{\"score\":\"1:0\",\"gamescore\":\"\",\"setscore\":\"1:0#0:0\",\"matchminute\":\"81\"}","ErrorStatus":-36,"ErrorMessage":"Market Inactive","Modified":1,"PlayerId":0,"TeamId":0,"Probability":0.0,"NewProbability":0.0,"CustomBetOddValue":0.0,"CustomBetNewOddValue":0.0,"CustomBetProbability":0.0,"CustomBetNewProbability":0.0,"CustomBetModified":0,"SportEventEventId":4916274},{"OddId":100001,"SpecialBetValueId":1,"ChangeSpecialBetValueInSlip":false,"NewSpecialBetValueId":1,"Symbol":null,"OddValue":2.66,"NewOddValue":2.64,"EventScoreMetaInfo":"{\"score\":\"0:0\",\"gamescore\":\"\",\"setscore\":\"0:0\",\"matchminute\":\"40\"}","ErrorStatus":0,"ErrorMessage":"","Modified":-1,"PlayerId":0,"TeamId":0,"Probability":0.0,"NewProbability":0.0,"CustomBetOddValue":0.0,"CustomBetNewOddValue":0.0,"CustomBetProbability":0.0,"CustomBetNewProbability":0.0,"CustomBetModified":0,"SportEventEventId":4928535}],"NotValidEvents":[4928535,4916274,4918528],"BetReferences":[],"CombineBetReference":0,"BetSlip":{"Combinations":[{"CounterLines":1,"TotalLines":6,"CombinationsProduced":6,"MultiplesSelections":1,"AverageMultiplierMin":1.96719093260706,"AverageMultiplierMax":1.96719093260706,"BonusMin":0.0,"BonusMax":0.0,"MinimumMultpilierWithBonus":1.07,"MaximumMultiplierWithBonus":2.66,"MinimumMultpilier":1.07,"MaximumMultiplier":2.66,"Amount":0.0,"AmountPerColumn":0.0,"Enabled":true},{"CounterLines":2,"TotalLines":6,"CombinationsProduced":15,"MultiplesSelections":1,"AverageMultiplierMin":3.86984016533146,"AverageMultiplierMax":3.86984016533146,"BonusMin":0.0,"BonusMax":0.0,"MinimumMultpilierWithBonus":1.4231,"MaximumMultiplierWithBonus":6.7298,"MinimumMultpilier":1.4231,"MaximumMultiplier":6.7298,"Amount":0.0,"AmountPerColumn":0.0,"Enabled":true},{"CounterLines":3,"TotalLines":6,"CombinationsProduced":20,"MultiplesSelections":1,"AverageMultiplierMin":7.61271448387866,"AverageMultiplierMax":7.61271448387866,"BonusMin":0.0,"BonusMax":0.0,"MinimumMultpilierWithBonus":3.472364,"MaximumMultiplierWithBonus":16.689904,"MinimumMultpilier":3.472364,"MaximumMultiplier":16.689904,"Amount":0.0,"AmountPerColumn":0.0,"Enabled":true},{"CounterLines":4,"TotalLines":6,"CombinationsProduced":15,"MultiplesSelections":1,"AverageMultiplierMin":14.9756629052126,"AverageMultiplierMax":14.9756629052126,"BonusMin":0.0,"BonusMax":0.0,"MinimumMultpilierWithBonus":8.61146272,"MaximumMultiplierWithBonus":40.72336576,"MinimumMultpilier":8.61146272,"MaximumMultiplier":40.72336576,"Amount":0.0,"AmountPerColumn":0.0,"Enabled":true},{"CounterLines":5,"TotalLines":6,"CombinationsProduced":6,"MultiplesSelections":1,"AverageMultiplierMin":29.4599882769142,"AverageMultiplierMax":29.4599882769142,"BonusMin":0.0,"BonusMax":0.0,"MinimumMultpilierWithBonus":21.7870006816,"MaximumMultiplierWithBonus":54.1620764608,"MinimumMultpilier":21.7870006816,"MaximumMultiplier":54.1620764608,"Amount":0.0,"AmountPerColumn":0.0,"Enabled":true},{"CounterLines":6,"TotalLines":6,"CombinationsProduced":1,"MultiplesSelections":1,"AverageMultiplierMin":57.953421813056,"AverageMultiplierMax":57.953421813056,"BonusMin":0.0,"BonusMax":0.0,"MinimumMultpilierWithBonus":57.953421813056,"MaximumMultiplierWithBonus":57.953421813056,"MinimumMultpilier":57.953421813056,"MaximumMultiplier":57.953421813056,"Amount":0.0,"AmountPerColumn":0.0,"Enabled":true}],"WhiteLabelId":3,"LiveWhiteLabelId":12,"SiteId":54,"MinimumAccepted":1,"GroupBonus":0.0,"ErrorFlag":0,"HasLive":true,"MultiplesBets":1,"NumberOfBankers":0,"NumberOfNoBankers":6,"IsFreeBet":false,"TotalOdds":57.953421813056,"System":0,"SystemClicked":false,"Events":[{"SportEventId":4919135,"Banker":false,"EventScoreMetaInfo":"","Selections":[{"SportEventId":4919135,"MarketId":185,"OddId":966,"SpecialBetValueId":1,"IsLive":false,"ChangeSpecialBetValueInSlip":false,"OddValue":2.53,"SpecialValue":0.0,"TeamId":0,"PlayerId":0,"TeamOrder":null,"Banker":false,"Minimum":1,"IsCustomBetSelection":false,"HasChanges":false,"Probability":0.4014}],"SlipEventLocalized":{"SportEventId":4919135,"EventCode":1,"Game":{"Id":1,"Name":"Soccer"},"Country":{"Id":601,"Name":"ENGLAND"},"Group":{"Id":50342,"Name":"MATCHES - 1X2 and other odds","AntePostMarkets":0,"MainType":0},"League":{"Id":1,"Name":"England Premier League"},"MatchDescription":"Manchester United - Tottenham","Team1":"Manchester United","Team2":"Tottenham","IsInvalid":false,"SelectionCollection":{"966_1_0_0":{"GameId":1,"SportEventId":4919135,"MarketId":185,"OddId":966,"SpecialBetValueId":1,"ChangeSpecialBetValueInSlip":false,"SpecialBetValue":"","Symbol":"1*","MarketName":"1X2 0%","MarketDescription":"What will the result be at the end of Regular time (FT).","OddName":"1","OddDescription":"1","SpecialValue":0.0,"TeamId":0,"PlayerId":0,"TeamOrder":null,"PlayerName":"","MarketNameWithSpecialValue":"1X2 0%","OddNameWithSpecialValue":"1","OddNewDescriptionWithSpecialValue":"1","SymbolWithSpecialValue":"1*","OddDescriptionWithSpecialValue":"1","OddValue":2.53,"MarketNameFromTemplate":"1X2 0%","OddNameFromTemplate":" Manchester United","IsCustomBetSelection":false,"CustomBetOddValue":0.0,"CustomBetProbability":0.0}},"IsActive":true,"Results":[],"ResultsString":"","LanguageId":1},"IsCustomBetEvent":false,"CustomBetOddValue":0.0,"CustomBetProbability":0.0},{"SportEventId":4928535,"Banker":false,"EventScoreMetaInfo":"{\"score\":\"0:0\",\"gamescore\":\"\",\"setscore\":\"0:0\",\"matchminute\":\"40\"}","Selections":[{"SportEventId":4928535,"MarketId":10001,"OddId":100001,"SpecialBetValueId":1,"IsLive":true,"ChangeSpecialBetValueInSlip":false,"OddValue":2.64,"SpecialValue":0.0,"TeamId":0,"PlayerId":0,"TeamOrder":null,"Banker":false,"Minimum":1,"IsCustomBetSelection":false,"HasChanges":false,"Probability":0.35570288}],"SlipEventLocalized":{"SportEventId":4928535,"EventCode":1,"Game":{"Id":1,"Name":"Soccer"},"Country":{"Id":430,"Name":"KOREA SOUTH"},"Group":{"Id":50342,"Name":"MATCHES - 1X2 and other odds","AntePostMarkets":0,"MainType":0},"League":{"Id":5827,"Name":"South Korea K League 1"},"MatchDescription":"Bucheon FC - Gyeongnam FC","Team1":"Bucheon FC","Team2":"Gyeongnam FC","IsInvalid":false,"SelectionCollection":{"100001_1_0_0":{"GameId":1,"SportEventId":4928535,"MarketId":10001,"OddId":100001,"SpecialBetValueId":1,"ChangeSpecialBetValueInSlip":false,"SpecialBetValue":"","Symbol":"10001-1","MarketName":"3way","MarketDescription":"3way","OddName":"1","OddDescription":"1","SpecialValue":0.0,"TeamId":0,"PlayerId":0,"TeamOrder":null,"PlayerName":"","MarketNameWithSpecialValue":"3way","OddNameWithSpecialValue":"1","OddNewDescriptionWithSpecialValue":"1","SymbolWithSpecialValue":"10001-1","OddDescriptionWithSpecialValue":"1","OddValue":2.64,"MarketNameFromTemplate":"3way","OddNameFromTemplate":" Bucheon FC","IsCustomBetSelection":false,"CustomBetOddValue":0.0,"CustomBetProbability":0.0}},"IsActive":true,"Results":[],"ResultsString":"","LanguageId":1},"IsCustomBetEvent":false,"CustomBetOddValue":0.0,"CustomBetProbability":0.0},{"SportEventId":4916274,"Banker":false,"EventScoreMetaInfo":"{\"score\":\"1:0\",\"gamescore\":\"\",\"setscore\":\"1:0#0:0\",\"matchminute\":\"81\"}","Selections":[{"SportEventId":4916274,"MarketId":10001,"OddId":100001,"SpecialBetValueId":1,"IsLive":true,"ChangeSpecialBetValueInSlip":false,"OddValue":0.0,"SpecialValue":0.0,"TeamId":0,"PlayerId":0,"TeamOrder":null,"Banker":false,"Minimum":1,"IsCustomBetSelection":false,"HasChanges":false,"Probability":0.0}],"SlipEventLocalized":{"SportEventId":4916274,"EventCode":1,"Game":{"Id":1,"Name":"Soccer"},"Country":{"Id":277,"Name":"AZERBAIJAN"},"Group":{"Id":50342,"Name":"MATCHES - 1X2 and other odds","AntePostMarkets":0,"MainType":0},"League":{"Id":7078,"Name":"Azerbaijan First Division"},"MatchDescription":"Zira Fk 2 - Energetik Mingechevir","Team1":"Zira Fk 2","Team2":"Energetik Mingechevir","IsInvalid":false,"SelectionCollection":{"100001_1_0_0":{"GameId":1,"SportEventId":4916274,"MarketId":10001,"OddId":100001,"SpecialBetValueId":1,"ChangeSpecialBetValueInSlip":false,"SpecialBetValue":"","Symbol":"10001-1","MarketName":"3way","MarketDescription":"3way","OddName":"1","OddDescription":"1","SpecialValue":0.0,"TeamId":0,"PlayerId":0,"TeamOrder":null,"PlayerName":"","MarketNameWithSpecialValue":"3way","OddNameWithSpecialValue":"1","OddNewDescriptionWithSpecialValue":"1","SymbolWithSpecialValue":"10001-1","OddDescriptionWithSpecialValue":"1","OddValue":0.0,"MarketNameFromTemplate":"3way","OddNameFromTemplate":" Zira Fk 2","IsCustomBetSelection":false,"CustomBetOddValue":0.0,"CustomBetProbability":0.0}},"IsActive":true,"Results":[],"ResultsString":"","LanguageId":1},"IsCustomBetEvent":false,"CustomBetOddValue":0.0,"CustomBetProbability":0.0},{"SportEventId":4918528,"Banker":false,"EventScoreMetaInfo":"{\"score\":\"0:0\",\"gamescore\":\"\",\"setscore\":\"0:0\",\"matchminute\":\"41\"}","Selections":[{"SportEventId":4918528,"MarketId":10001,"OddId":100002,"SpecialBetValueId":1,"IsLive":true,"ChangeSpecialBetValueInSlip":false,"OddValue":2.46,"SpecialValue":0.0,"TeamId":0,"PlayerId":0,"TeamOrder":null,"Banker":false,"Minimum":1,"IsCustomBetSelection":false,"HasChanges":false,"Probability":0.37025102}],"SlipEventLocalized":{"SportEventId":4918528,"EventCode":1,"Game":{"Id":1,"Name":"Soccer"},"Country":{"Id":399,"Name":"ETHIOPIA"},"Group":{"Id":50342,"Name":"MATCHES - 1X2 and other odds","AntePostMarkets":0,"MainType":0},"League":{"Id":7661,"Name":"Ethiopia Premier League "},"MatchDescription":"Arba Minch Kenema - Hadiya Hossana FC","Team1":"Arba Minch Kenema","Team2":"Hadiya Hossana FC","IsInvalid":false,"SelectionCollection":{"100002_1_0_0":{"GameId":1,"SportEventId":4918528,"MarketId":10001,"OddId":100002,"SpecialBetValueId":1,"ChangeSpecialBetValueInSlip":false,"SpecialBetValue":"","Symbol":"10001-x","MarketName":"3way","MarketDescription":"3way","OddName":"X","OddDescription":"x","SpecialValue":0.0,"TeamId":0,"PlayerId":0,"TeamOrder":null,"PlayerName":"","MarketNameWithSpecialValue":"3way","OddNameWithSpecialValue":"X","OddNewDescriptionWithSpecialValue":"x","SymbolWithSpecialValue":"10001-x","OddDescriptionWithSpecialValue":"x","OddValue":2.46,"MarketNameFromTemplate":"3way","OddNameFromTemplate":" Draw","IsCustomBetSelection":false,"CustomBetOddValue":0.0,"CustomBetProbability":0.0}},"IsActive":true,"Results":[],"ResultsString":"","LanguageId":1},"IsCustomBetEvent":false,"CustomBetOddValue":0.0,"CustomBetProbability":0.0},{"SportEventId":4917809,"Banker":false,"EventScoreMetaInfo":"{\"score\":\"1:2\",\"gamescore\":\"\",\"setscore\":\"1:2\",\"matchminute\":\"39\"}","Selections":[{"SportEventId":4917809,"MarketId":10001,"OddId":100003,"SpecialBetValueId":1,"IsLive":true,"ChangeSpecialBetValueInSlip":false,"OddValue":2.44,"SpecialValue":0.0,"TeamId":0,"PlayerId":0,"TeamOrder":null,"Banker":false,"Minimum":1,"IsCustomBetSelection":false,"HasChanges":false,"Probability":0.37361097}],"SlipEventLocalized":{"SportEventId":4917809,"EventCode":1,"Game":{"Id":1,"Name":"Soccer"},"Country":{"Id":211,"Name":"ITALY "},"Group":{"Id":50342,"Name":"MATCHES - 1X2 and other odds","AntePostMarkets":0,"MainType":0},"League":{"Id":7238,"Name":"Italy Primavera Cup"},"MatchDescription":"Empoli - Ascoli","Team1":"Empoli","Team2":"Ascoli","IsInvalid":false,"SelectionCollection":{"100003_1_0_0":{"GameId":1,"SportEventId":4917809,"MarketId":10001,"OddId":100003,"SpecialBetValueId":1,"ChangeSpecialBetValueInSlip":false,"SpecialBetValue":"","Symbol":"10001-2","MarketName":"3way","MarketDescription":"3way","OddName":"2","OddDescription":"2","SpecialValue":0.0,"TeamId":0,"PlayerId":0,"TeamOrder":null,"PlayerName":"","MarketNameWithSpecialValue":"3way","OddNameWithSpecialValue":"2","OddNewDescriptionWithSpecialValue":"2","SymbolWithSpecialValue":"10001-2","OddDescriptionWithSpecialValue":"2","OddValue":2.44,"MarketNameFromTemplate":"3way","OddNameFromTemplate":" Ascoli","IsCustomBetSelection":false,"CustomBetOddValue":0.0,"CustomBetProbability":0.0}},"IsActive":true,"Results":[],"ResultsString":"","LanguageId":1},"IsCustomBetEvent":false,"CustomBetOddValue":0.0,"CustomBetProbability":0.0},{"SportEventId":4917578,"Banker":false,"EventScoreMetaInfo":"{\"score\":\"0:1\",\"gamescore\":\"\",\"setscore\":\"0:1#0:0\",\"matchminute\":\"83\"}","Selections":[{"SportEventId":4917578,"MarketId":10001,"OddId":100003,"SpecialBetValueId":1,"IsLive":true,"ChangeSpecialBetValueInSlip":false,"OddValue":1.33,"SpecialValue":0.0,"TeamId":0,"PlayerId":0,"TeamOrder":null,"Banker":false,"Minimum":1,"IsCustomBetSelection":false,"HasChanges":false,"Probability":0.70604725}],"SlipEventLocalized":{"SportEventId":4917578,"EventCode":1,"Game":{"Id":1,"Name":"Soccer"},"Country":{"Id":455,"Name":"MYANMAR"},"Group":{"Id":50343,"Name":"ONLY LIVE MATCHES - 1X2 and other odds","AntePostMarkets":0,"MainType":0},"League":{"Id":7467,"Name":"Myanmar National League"},"MatchDescription":"Myawady Fc - Yadanarbon","Team1":"Myawady Fc","Team2":"Yadanarbon","IsInvalid":false,"SelectionCollection":{"100003_1_0_0":{"GameId":1,"SportEventId":4917578,"MarketId":10001,"OddId":100003,"SpecialBetValueId":1,"ChangeSpecialBetValueInSlip":false,"SpecialBetValue":"","Symbol":"10001-2","MarketName":"3way","MarketDescription":"3way","OddName":"2","OddDescription":"2","SpecialValue":0.0,"TeamId":0,"PlayerId":0,"TeamOrder":null,"PlayerName":"","MarketNameWithSpecialValue":"3way","OddNameWithSpecialValue":"2","OddNewDescriptionWithSpecialValue":"2","SymbolWithSpecialValue":"10001-2","OddDescriptionWithSpecialValue":"2","OddValue":1.33,"MarketNameFromTemplate":"3way","OddNameFromTemplate":" Yadanarbon","IsCustomBetSelection":false,"CustomBetOddValue":0.0,"CustomBetProbability":0.0}},"IsActive":false,"Results":[],"ResultsString":"","LanguageId":1},"IsCustomBetEvent":false,"CustomBetOddValue":0.0,"CustomBetProbability":0.0}]},"RiskClientResponse":{"AuthorisationMaxEventAmount":0.0,"AuthorisationSelectionMultipe":0.0,"AuthorisationSportEventId":0,"AuthorisationSelection":0,"Status":0},"TotalBetAmount":0.0,"RiskManagerResponse":{"AuthorisationRequestId":0,"ProposedAmount":0.0,"CheckForNewAuthorisation":false,"ErrorCode":0},"BookBetId":0,"PossibleDelayBeforeAuth":0,"RequiresAuthorisation":false,"ErrorMessage":"Odds Have Changed.","System":1,"CheckHash":0,"Repeat":1,"PlacingBet":false,"ResponseStatus":null},"BookBet":{"MaxDateValid":"0001-01-01T00:00:00","MinDateValid":"0001-01-01T00:00:00","TotalAmount":0.0,"SessionSystem":0,"SiteId":0,"Description":null,"StartShow":"0001-01-01T00:00:00","EndShow":"0001-01-01T00:00:00","Active":0,"BookBetGroupId":0,"GroupTitle":null,"GroupDescription":null,"BookBetEvents":[],"BookBetDetails":[],"BookBetId":0},"BetSlipCheck":"4919135bnk1854919135_185_966_2.53_0.0_1_0.0n2.531CENV4928535bnkNVD100014928535_10001_100001_2.64_0.0_1_0.0nd2.641CENV4916274bnkNVD100014916274_10001_100001_0_0.0_1_0.0nd01CENV4918528bnkNVD100014918528_10001_100002_2.46_0.0_1_0.0nd2.461C4917809bnk100014917809_10001_100003_2.44_0.0_1_0.0n2.441C4917578bnk100014917578_10001_100003_1.33_0.0_1_0.0n1.331C"}
